mkdocs_color_swatch_plugin/__init__.py
mkdocs_color_swatch_plugin/assets/color-swatch.css
mkdocs_color_swatch_plugin/assets/color-swatch.js
mkdocs_color_swatch_plugin/color_swatch.py
mkdocs_color_swatch_plugin/plugin.py
mkdocs_color_swatch_plugin-0.3.0.dist-info/LICENSE
mkdocs_color_swatch_plugin-0.3.0.dist-info/METADATA
mkdocs_color_swatch_plugin-0.3.0.dist-info/WHEEL
mkdocs_color_swatch_plugin-0.3.0.dist-info/entry_points.txt
mkdocs_color_swatch_plugin-0.3.0.dist-info/RECORD
