Metadata-Version: 2.3
Name: mkdocs-color-swatch-plugin
Version: 0.3.0
Summary: A MkDocs plugin for inline color swatches with tooltip and hover effects
License: MIT
Keywords: mkdocs,plugin,markdown,color,tooltip
Author: Fabian Eulitz
Author-email: dev@sustineo.de
Requires-Python: >=3.10
Classifier: License :: OSI Approved :: MIT License
Classifier: Programming Language :: Python :: 3
Classifier: Programming Language :: Python :: 3.10
Classifier: Programming Language :: Python :: 3.11
Classifier: Programming Language :: Python :: 3.12
Classifier: Programming Language :: Python :: 3.13
Requires-Dist: beautifulsoup4 (>=4.13.4,<5.0.0)
Requires-Dist: markdown (>=3.8,<4.0)
Requires-Dist: mkdocs (>=1.6.1,<2.0.0)
